<?xml version="1.0" encoding="ISO-8859-1" ?>
<!DOCTYPE scenario SYSTEM "sipp.dtd">

<!-- This program is free software; you can redistribute it and/or      -->
<!-- modify it under the terms of the GNU General Public License as     -->
<!-- published by the Free Software Foundation; either version 2 of the -->
<!-- License, or (at your option) any later version.      -->
<!--     -->
<!-- This program is distributed in the hope that it will be useful,    -->
<!-- but WITHOUT ANY WARRANTY; without even the implied warranty of     -->
<!-- MERCHANTABILITY or FITNESS FOR A PARTICULAR PURPOSE.  See the      -->
<!-- GNU General Public License for more details.  -->
<!--     -->
<!-- You should have received a copy of the GNU General Public License  -->
<!-- along with this program; if not, write to the -->
<!-- Free Software Foundation, Inc., -->
<!-- 59 Temple Place, Suite 330, Boston, MA  02111-1307 USA      -->
<!--
         INVITE sip:[field1]@10.6.0.153:5050;user=phone SIP/2.0
    INVITE sip:[field1]@[remote_ip]:[remote_port];user=phone SIP/2.0
       -->
<!--   Sipp default 'uac' scenario.  -->
<!--     Contact: <sip:[local_ip]:[local_port];transport=[transport];Dpt=eaea-200;Hpt=8e68_16;CxtId=4;TRC=ffffffff-ffffffff>;video;+g.3gpp.icsi-ref="urn%3Aurn-7%3A3gpp-service.ims.icsi.mmtel"
                      Accept-Contact: *;+g.3gpp.icsi-ref="urn%3Aurn-7%3A3gpp-service.ims.icsi.mmtel";video
                 P-Visited-Network-ID: "ims.mnc001.mcc455.3gppnetwork.org"
                     P-Early-Media: supported,gated
                         P-Asserted-Identity: <sip:+85362869578@ims.mnc001.mcc455.3gppnetwork.org;cpc=ordinary>
                             P-Asserted-Identity: <tel:+85362869578;cpc=ordinary>
                                 P-Access-Network-Info: IEEE-802.11;i-wlan-node-id=587f669fed27;country=Macau
                                     P-Charging-Vector: icid-value="ctm-pcscf01.191.3902.20161024164947";orig-ioi=tec-scscf01.ims.mnc001.mcc455.3gppnetwork.org;pdngw=202.175.4.221;eps-info="eps-item=1;eps-sig=no;ecid=CCA94B45;flow-id=({1,1},{1,2})"
Session-Expires: 1800;refresher=uac
                                     -->

    <!--Via: SIP/2.0/[transport] [local_ip]:[local_port];branch=[branch]-->
<scenario name="Basic Sipstone UAC">
    <!-- In client mode (sipp placing calls), the Call-ID MUST be  -->
    <!-- generated by sipp. To do so, use [call_id] token.  -->
    <send >
    <![CDATA[
    INVITE sip:[field1]@[remote_ip]:[remote_port];user=phone SIP/2.0
    Via: SIP/2.0/[transport] [local_ip]:[local_port];branch=[branch]
    From: ua[call_number] <sip:[field0]@[local_ip]:[local_port]>;tag=[call_number]
    To: sut <sip:[field1]@[remote_ip]:[remote_port]>
   Call-ID: [call_id]
   Contact: <sip:[local_ip]:[local_port];transport=[transport];Dpt=eaea-200;Hpt=8e68_16;CxtId=4;TRC=ffffffff-ffffffff>;video;+g.3gpp.icsi-ref="urn%3Aurn-7%3A3gpp-service.ims.icsi.mmtel"
CSeq: 1 INVITE
X-Call-Record: both
Max-Forwards: 62
Accept: application/sdp
Privacy: none
Session-Expires: 1800;refresher=uac
Supported: 100rel,precondition,timer,record-aware
Allow: INVITE,ACK,BYE,CANCEL,PRACK,INFO,REFER,UPDATE,OPTIONS,SUBSCRIBE,NOTIFY
Min-SE: 900
Content-Type: application/sdp
Content-Length: [len]

v=0
o=HPE-AS 4217 2 IN IP4 SBC.dialogic.com 
s=-
    c=IN IP4 [media_ip]
t=0 0
m=audio [auto_media_port+1] RTP/AVP 0 8 
    c=IN IP4 [media_ip]
a=rtpmap:0 PCMU/8000
a=rtpmap:8 PCMA/8000


   ]]>
    </send>
    <!--a=rtpmap:0 PCMU/8000-->

    <recv response="100" optional="true" />

    <recv response="500" optional="true" next="1">
    <action>
    <ereg regexp=".*" search_in="hdr" header="Via:" assign_to="via" />
    <ereg regexp=".*" search_in="hdr" header="To:" assign_to="to" />
    <ereg regexp=".*" search_in="hdr" header="From:" assign_to="from" />
    </action>
    </recv>
    <recv response="400" optional="true" next="1">
    <action>
    <ereg regexp=".*" search_in="hdr" header="Via:" assign_to="via" />
    <ereg regexp=".*" search_in="hdr" header="To:" assign_to="to" />
    <ereg regexp=".*" search_in="hdr" header="From:" assign_to="from" />
    </action>
    </recv>
    <recv response="404" optional="true" next="1">
    <action>
    <ereg regexp=".*" search_in="hdr" header="Via:" assign_to="via" />
    <ereg regexp=".*" search_in="hdr" header="To:" assign_to="to" />
    <ereg regexp=".*" search_in="hdr" header="From:" assign_to="from" />
    </action>
    </recv>
    <recv response="408" optional="true" next="1">
    <action>
    <ereg regexp=".*" search_in="hdr" header="Via:" assign_to="via" />
    <ereg regexp=".*" search_in="hdr" header="To:" assign_to="to" />
    <ereg regexp=".*" search_in="hdr" header="From:" assign_to="from" />
    </action>
    </recv>

    <recv response="503" optional="true" next="1">
    <action>
    <ereg regexp=".*" search_in="hdr" header="Via:" assign_to="via" />
    <ereg regexp=".*" search_in="hdr" header="To:" assign_to="to" />
    <ereg regexp=".*" search_in="hdr" header="From:" assign_to="from" />
    </action>
    </recv>



    <recv response="183" >
             <action>
    <ereg regexp=".*" search_in="hdr" header="Via:" assign_to="via" />
    <ereg regexp=".*" search_in="hdr" header="To:" assign_to="to" />
    <ereg regexp=".*" search_in="hdr" header="From:" assign_to="from" />
    <ereg regexp=".*" search_in="hdr" header="CSeq:" assign_to="2" />
    <ereg regexp=".*" search_in="hdr" header="RSeq:" assign_to="1" />
    </action>
    </recv>

    <send  >
    <![CDATA[
    PRACK sip:[field1]@[remote_ip]:[remote_port] SIP/2.0
    Via: SIP/2.0/[transport] [local_ip]:[local_port];branch=z9hG4bK947f.c92cde7e88864cbc9b552394784c
    From: sipp <sip:sipp@[local_ip]:[local_port]>;tag=[call_number]
    To: sut <sip:[service]@[remote_ip]:[remote_port]>[peer_tag_param]
    Call-ID: [call_id]
    CSeq: 2 PRACK
    RAck: [$1][$2]
    Max-Forwards: 70
    Content-Length: 0
   ]]>
    </send>

    <recv response="200" >
             </recv>
  <nop>
    <action>
      <exec play_pcap_audio="/root/holly/pcap/g711a.pcap"/>
        </action>
          </nop>

<pause distribution="uniform" min="10000" max="10000"/>
    <recv response="200" >
    </recv>



    <send  >
    <![CDATA[
    ACK sip:[field1]@[remote_ip]:[remote_port] SIP/2.0
    Via: SIP/2.0/UDP [local_ip]:[local_port];branch=[branch]
    From: [field0] <sip:[field0]@[local_ip]:[local_port]>;tag=[call_number]
    To: [field1] <sip:[field1]@[remote_ip]:[remote_port]>[peer_tag_param]
    Call-ID: [call_id]
    CSeq: 1 ACK
    Max-Forwards: 70
    Content-Length: 0
   ]]>
    </send>

 <label id="5"/>

  <nop>
    <action>
      <exec play_pcap_audio="/root/holly/pcap/g711a.pcap"/>
        </action>
          </nop>

<pause distribution="uniform" min="10000" max="10000"/>
 <label id="4"/>
    <send lost="0">
    <!--send lost="1"-->
    <![CDATA[

    BYE sip:[field1]@[remote_ip]:[remote_port] SIP/2.0
    Via: SIP/2.0/UDP [local_ip]:[local_port];branch=[branch]
    From: [field0] <sip:[field0]@[local_ip]:[local_port]>;tag=[call_number]
    To: [field1] <sip:[field1]@[remote_ip]:[remote_port]>[peer_tag_param]
    Call-ID: [call_id]
    CSeq: 10 BYE
    Max-Forwards: 70
    Content-Length:0

    ]]>
    </send>

    <recv response="200" crlf="true" optional="true" next="2">
    </recv>
    <recv request="BYE" next="2" optional="true">
    </recv>
    <recv request="UPDATE" next="7" timeout="31000" ontimeout="6">
    </recv>

 <label id="7"/>
    <send next="5">
   <![CDATA[

    SIP/2.0 200 OK
    [last_Via:]
    [last_From:]
    [last_To:]
    [last_Call-ID:]
    [last_CSeq:]
    Contact: <sip:[local_ip]:[local_port];transport=[transport]>
    Content-Length: 0

    ]]>
    </send>

 <label id="6"/>
    <pause distribution="uniform" min="500" max="1000"/>
    <send retrans="500">
    <![CDATA[

    BYE sip:[field1]@[remote_ip]:[remote_port] SIP/2.0
    Via: SIP/2.0/UDP [local_ip]:[local_port];branch=[branch]
    From: [field0] <sip:[field0]@[local_ip]:[local_port]>;tag=[call_number]
    To: [field1] <sip:[field1]@[remote_ip]:[remote_port]>[peer_tag_param]
    Call-ID: [call_id]
    CSeq: 10 BYE
    Max-Forwards: 70
    Content-Length:0

    ]]>
    </send>

    <recv response="200" crlf="true" next="2">
    </recv>
    <pause distribution="uniform" min="5000" max="10000"/>

 <label id="1"/>
    <send next="2">
   <![CDATA[
    ACK sip:[field1]@[remote_ip]:[remote_port] SIP/2.0
    Via: [$via]
    From: [$to]
    To: [$from]
    [last_Call-ID:]
    CSeq: [cseq] ACK
    Max-Forwards: 70

    ]]>
    </send>

<label id="8"/>
    <send next="2">
   <![CDATA[

    SIP/2.0 200 OK
    [last_Via:]
    [last_From:]
    [last_To:]
    [last_Call-ID:]
    [last_CSeq:]
    Contact: <sip:[local_ip]:[local_port];transport=[transport]>
    Content-Length: 0

    ]]>
    </send>



 <label id="2"/>

    <!-- definition of the response time repartition table (unit is ms)   -->
    <!-- ResponseTimeRepartition value="10, 20, 30, 40, 50, 100, 150, 200"/ -->

    <!-- definition of the call length repartition table (unit is ms)     -->
    <!-- CallLengthRepartition value="10, 50, 100, 500, 1000, 5000, 10000"/ -->
</scenario>

